Metadata-Version: 1.0
Name: derek-test-distributions
Version: 0.1
Summary: Binomial and Gaussian distributions
Home-page: UNKNOWN
Author: Derek Chen
Author-email: UNKNOWN
License: UNKNOWN
Platform: UNKNOWN
